README
setup.cfg
setup.py
luijo/__init__.py
luijo/config.py
luijo/errors.py
luijo/mock.py
luijo/targets.py
luijo.egg-info/PKG-INFO
luijo.egg-info/SOURCES.txt
luijo.egg-info/dependency_links.txt
luijo.egg-info/requires.txt
luijo.egg-info/top_level.txt