Metadata-Version: 1.2
Name: luijo
Version: 0.0.18
Summary: Extensions for Spotify Luigi
Home-page: https://github.com/patdaburu/luijo.git
Author: Pat Daburu
Author-email: patb@daburu.net
License: MIT
Download-URL: https://github.com/patdaburu/luijo/archive/0.0.18.tar.gz
Platform: UNKNOWN
Classifier: Development Status :: 3 - Alpha
Classifier: Intended Audience :: Developers
Classifier: Topic :: Software Development :: Libraries
Classifier: License :: OSI Approved :: MIT License
Classifier: Programming Language :: Python :: 3.6
Requires-Python: >=3.6.1
